<?xml version="1.0" encoding="utf-8"?>
<ArrayOfEngineer xmlns:xsi="http://www.w3.org/2001/XMLSchema-instance" xmlns:xsd="http://www.w3.org/2001/XMLSchema">
  <Engineer>
    <ID>267151768</ID>
    <Name>Dani</Name>
    <Level>Junior</Level>
    <Cost>283</Cost>
    <Email>Dani@gmail.com</Email>
  </Engineer>
  <Engineer>
    <ID>388986334</ID>
    <Name>Eli</Name>
    <Level>EIT</Level>
    <Cost>154</Cost>
    <Email>Eli@gmail.com</Email>
  </Engineer>
  <Engineer>
    <ID>303830100</ID>
    <Name>Yair</Name>
    <Level>Junior</Level>
    <Cost>164</Cost>
    <Email>Yair@gmail.com</Email>
  </Engineer>
  <Engineer>
    <ID>256881860</ID>
    <Name>Ariela</Name>
    <Level>EIT</Level>
    <Cost>114</Cost>
    <Email>Ariela@gmail.com</Email>
  </Engineer>
  <Engineer>
    <ID>204983227</ID>
    <Name>Dina</Name>
    <Level>Junior</Level>
    <Cost>322</Cost>
    <Email>Dina@gmail.com</Email>
  </Engineer>
  <Engineer>
    <ID>389962282</ID>
    <Name>Shira</Name>
    <Level>Senior</Level>
    <Cost>110</Cost>
    <Email>Shira@gmail.com</Email>
  </Engineer>
  <Engineer>
    <ID>202564801</ID>
    <Name>Lea</Name>
    <Level>EIT</Level>
    <Cost>219</Cost>
    <Email>Lea@gmail.com</Email>
  </Engineer>
  <Engineer>
    <ID>269389711</ID>
    <Name>Rachel</Name>
    <Level>EIT</Level>
    <Cost>101</Cost>
    <Email>Rachel@gmail.com</Email>
  </Engineer>
  <Engineer>
    <ID>326073455</ID>
    <Name>Alice</Name>
    <Level>Senior</Level>
    <Cost>332</Cost>
    <Email>Alice@gmail.com</Email>
  </Engineer>
  <Engineer>
    <ID>242345599</ID>
    <Name>Dani</Name>
    <Level>Junior</Level>
    <Cost>160</Cost>
    <Email>Dani@gmail.com</Email>
  </Engineer>
  <Engineer>
    <ID>269227989</ID>
    <Name>Eli</Name>
    <Level>EIT</Level>
    <Cost>112</Cost>
    <Email>Eli@gmail.com</Email>
  </Engineer>
  <Engineer>
    <ID>375283798</ID>
    <Name>Yair</Name>
    <Level>Junior</Level>
    <Cost>296</Cost>
    <Email>Yair@gmail.com</Email>
  </Engineer>
  <Engineer>
    <ID>266627417</ID>
    <Name>Ariela</Name>
    <Level>EIT</Level>
    <Cost>296</Cost>
    <Email>Ariela@gmail.com</Email>
  </Engineer>
  <Engineer>
    <ID>264010538</ID>
    <Name>Dina</Name>
    <Level>Junior</Level>
    <Cost>267</Cost>
    <Email>Dina@gmail.com</Email>
  </Engineer>
  <Engineer>
    <ID>301465837</ID>
    <Name>Shira</Name>
    <Level>Senior</Level>
    <Cost>131</Cost>
    <Email>Shira@gmail.com</Email>
  </Engineer>
  <Engineer>
    <ID>383177889</ID>
    <Name>Lea</Name>
    <Level>EIT</Level>
    <Cost>217</Cost>
    <Email>Lea@gmail.com</Email>
  </Engineer>
  <Engineer>
    <ID>305163285</ID>
    <Name>Rachel</Name>
    <Level>EIT</Level>
    <Cost>326</Cost>
    <Email>Rachel@gmail.com</Email>
  </Engineer>
  <Engineer>
    <ID>355037662</ID>
    <Name>Alice</Name>
    <Level>Senior</Level>
    <Cost>143</Cost>
    <Email>Alice@gmail.com</Email>
  </Engineer>
  <Engineer>
    <ID>361679057</ID>
    <Name>Dani</Name>
    <Level>Junior</Level>
    <Cost>299</Cost>
    <Email>Dani@gmail.com</Email>
  </Engineer>
  <Engineer>
    <ID>200518235</ID>
    <Name>Eli</Name>
    <Level>EIT</Level>
    <Cost>314</Cost>
    <Email>Eli@gmail.com</Email>
  </Engineer>
  <Engineer>
    <ID>354641028</ID>
    <Name>Yair</Name>
    <Level>Junior</Level>
    <Cost>264</Cost>
    <Email>Yair@gmail.com</Email>
  </Engineer>
  <Engineer>
    <ID>273822184</ID>
    <Name>Ariela</Name>
    <Level>EIT</Level>
    <Cost>277</Cost>
    <Email>Ariela@gmail.com</Email>
  </Engineer>
  <Engineer>
    <ID>293975461</ID>
    <Name>Dina</Name>
    <Level>Junior</Level>
    <Cost>334</Cost>
    <Email>Dina@gmail.com</Email>
  </Engineer>
  <Engineer>
    <ID>259095365</ID>
    <Name>Shira</Name>
    <Level>Senior</Level>
    <Cost>130</Cost>
    <Email>Shira@gmail.com</Email>
  </Engineer>
  <Engineer>
    <ID>303266145</ID>
    <Name>Lea</Name>
    <Level>EIT</Level>
    <Cost>260</Cost>
    <Email>Lea@gmail.com</Email>
  </Engineer>
  <Engineer>
    <ID>369073774</ID>
    <Name>Rachel</Name>
    <Level>EIT</Level>
    <Cost>163</Cost>
    <Email>Rachel@gmail.com</Email>
  </Engineer>
  <Engineer>
    <ID>332327974</ID>
    <Name>Alice</Name>
    <Level>Senior</Level>
    <Cost>237</Cost>
    <Email>Alice@gmail.com</Email>
  </Engineer>
  <Engineer>
    <ID>375904058</ID>
    <Name>Dani</Name>
    <Level>Junior</Level>
    <Cost>124</Cost>
    <Email>Dani@gmail.com</Email>
  </Engineer>
  <Engineer>
    <ID>266173151</ID>
    <Name>Eli</Name>
    <Level>EIT</Level>
    <Cost>302</Cost>
    <Email>Eli@gmail.com</Email>
  </Engineer>
  <Engineer>
    <ID>238385919</ID>
    <Name>Yair</Name>
    <Level>Junior</Level>
    <Cost>157</Cost>
    <Email>Yair@gmail.com</Email>
  </Engineer>
  <Engineer>
    <ID>272000831</ID>
    <Name>Ariela</Name>
    <Level>EIT</Level>
    <Cost>204</Cost>
    <Email>Ariela@gmail.com</Email>
  </Engineer>
  <Engineer>
    <ID>318291495</ID>
    <Name>Dina</Name>
    <Level>Junior</Level>
    <Cost>144</Cost>
    <Email>Dina@gmail.com</Email>
  </Engineer>
  <Engineer>
    <ID>202384828</ID>
    <Name>Shira</Name>
    <Level>Senior</Level>
    <Cost>146</Cost>
    <Email>Shira@gmail.com</Email>
  </Engineer>
  <Engineer>
    <ID>361449035</ID>
    <Name>Lea</Name>
    <Level>EIT</Level>
    <Cost>288</Cost>
    <Email>Lea@gmail.com</Email>
  </Engineer>
  <Engineer>
    <ID>255114762</ID>
    <Name>Rachel</Name>
    <Level>EIT</Level>
    <Cost>248</Cost>
    <Email>Rachel@gmail.com</Email>
  </Engineer>
  <Engineer>
    <ID>355950985</ID>
    <Name>Alice</Name>
    <Level>Senior</Level>
    <Cost>268</Cost>
    <Email>Alice@gmail.com</Email>
  </Engineer>
  <Engineer>
    <ID>399015520</ID>
    <Name>Dani</Name>
    <Level>Junior</Level>
    <Cost>188</Cost>
    <Email>Dani@gmail.com</Email>
  </Engineer>
  <Engineer>
    <ID>238495169</ID>
    <Name>Eli</Name>
    <Level>EIT</Level>
    <Cost>250</Cost>
    <Email>Eli@gmail.com</Email>
  </Engineer>
  <Engineer>
    <ID>251381948</ID>
    <Name>Yair</Name>
    <Level>Junior</Level>
    <Cost>335</Cost>
    <Email>Yair@gmail.com</Email>
  </Engineer>
  <Engineer>
    <ID>284980631</ID>
    <Name>Ariela</Name>
    <Level>EIT</Level>
    <Cost>222</Cost>
    <Email>Ariela@gmail.com</Email>
  </Engineer>
  <Engineer>
    <ID>226600423</ID>
    <Name>Dina</Name>
    <Level>Junior</Level>
    <Cost>114</Cost>
    <Email>Dina@gmail.com</Email>
  </Engineer>
  <Engineer>
    <ID>376941436</ID>
    <Name>Shira</Name>
    <Level>Senior</Level>
    <Cost>338</Cost>
    <Email>Shira@gmail.com</Email>
  </Engineer>
  <Engineer>
    <ID>387118934</ID>
    <Name>Lea</Name>
    <Level>EIT</Level>
    <Cost>163</Cost>
    <Email>Lea@gmail.com</Email>
  </Engineer>
  <Engineer>
    <ID>252370170</ID>
    <Name>Rachel</Name>
    <Level>EIT</Level>
    <Cost>207</Cost>
    <Email>Rachel@gmail.com</Email>
  </Engineer>
  <Engineer>
    <ID>252901242</ID>
    <Name>Alice</Name>
    <Level>Senior</Level>
    <Cost>204</Cost>
    <Email>Alice@gmail.com</Email>
  </Engineer>
  <Engineer>
    <ID>361845062</ID>
    <Name>Dani</Name>
    <Level>Junior</Level>
    <Cost>116</Cost>
    <Email>Dani@gmail.com</Email>
  </Engineer>
  <Engineer>
    <ID>297260681</ID>
    <Name>Eli</Name>
    <Level>EIT</Level>
    <Cost>129</Cost>
    <Email>Eli@gmail.com</Email>
  </Engineer>
  <Engineer>
    <ID>386856794</ID>
    <Name>Yair</Name>
    <Level>Junior</Level>
    <Cost>170</Cost>
    <Email>Yair@gmail.com</Email>
  </Engineer>
  <Engineer>
    <ID>291616100</ID>
    <Name>Ariela</Name>
    <Level>EIT</Level>
    <Cost>320</Cost>
    <Email>Ariela@gmail.com</Email>
  </Engineer>
  <Engineer>
    <ID>384535535</ID>
    <Name>Dina</Name>
    <Level>Junior</Level>
    <Cost>195</Cost>
    <Email>Dina@gmail.com</Email>
  </Engineer>
  <Engineer>
    <ID>234357983</ID>
    <Name>Shira</Name>
    <Level>Senior</Level>
    <Cost>185</Cost>
    <Email>Shira@gmail.com</Email>
  </Engineer>
  <Engineer>
    <ID>223084311</ID>
    <Name>Lea</Name>
    <Level>EIT</Level>
    <Cost>126</Cost>
    <Email>Lea@gmail.com</Email>
  </Engineer>
  <Engineer>
    <ID>349950454</ID>
    <Name>Rachel</Name>
    <Level>EIT</Level>
    <Cost>271</Cost>
    <Email>Rachel@gmail.com</Email>
  </Engineer>
  <Engineer>
    <ID>318205343</ID>
    <Name>Alice</Name>
    <Level>Senior</Level>
    <Cost>340</Cost>
    <Email>Alice@gmail.com</Email>
  </Engineer>
  <Engineer>
    <ID>341017971</ID>
    <Name>Dani</Name>
    <Level>Junior</Level>
    <Cost>111</Cost>
    <Email>Dani@gmail.com</Email>
  </Engineer>
  <Engineer>
    <ID>311860721</ID>
    <Name>Eli</Name>
    <Level>EIT</Level>
    <Cost>267</Cost>
    <Email>Eli@gmail.com</Email>
  </Engineer>
  <Engineer>
    <ID>257159163</ID>
    <Name>Yair</Name>
    <Level>Junior</Level>
    <Cost>193</Cost>
    <Email>Yair@gmail.com</Email>
  </Engineer>
  <Engineer>
    <ID>238045561</ID>
    <Name>Ariela</Name>
    <Level>EIT</Level>
    <Cost>141</Cost>
    <Email>Ariela@gmail.com</Email>
  </Engineer>
  <Engineer>
    <ID>365236888</ID>
    <Name>Dina</Name>
    <Level>Junior</Level>
    <Cost>132</Cost>
    <Email>Dina@gmail.com</Email>
  </Engineer>
  <Engineer>
    <ID>271343723</ID>
    <Name>Shira</Name>
    <Level>Senior</Level>
    <Cost>241</Cost>
    <Email>Shira@gmail.com</Email>
  </Engineer>
  <Engineer>
    <ID>227825772</ID>
    <Name>Lea</Name>
    <Level>EIT</Level>
    <Cost>139</Cost>
    <Email>Lea@gmail.com</Email>
  </Engineer>
  <Engineer>
    <ID>354235145</ID>
    <Name>Rachel</Name>
    <Level>EIT</Level>
    <Cost>154</Cost>
    <Email>Rachel@gmail.com</Email>
  </Engineer>
  <Engineer>
    <ID>211202492</ID>
    <Name>Alice</Name>
    <Level>Senior</Level>
    <Cost>149</Cost>
    <Email>Alice@gmail.com</Email>
  </Engineer>
  <Engineer>
    <ID>256068405</ID>
    <Name>Dani</Name>
    <Level>Junior</Level>
    <Cost>117</Cost>
    <Email>Dani@gmail.com</Email>
  </Engineer>
  <Engineer>
    <ID>338040149</ID>
    <Name>Eli</Name>
    <Level>EIT</Level>
    <Cost>153</Cost>
    <Email>Eli@gmail.com</Email>
  </Engineer>
  <Engineer>
    <ID>359006259</ID>
    <Name>Yair</Name>
    <Level>Junior</Level>
    <Cost>131</Cost>
    <Email>Yair@gmail.com</Email>
  </Engineer>
  <Engineer>
    <ID>208380573</ID>
    <Name>Ariela</Name>
    <Level>EIT</Level>
    <Cost>214</Cost>
    <Email>Ariela@gmail.com</Email>
  </Engineer>
  <Engineer>
    <ID>307982207</ID>
    <Name>Dina</Name>
    <Level>Junior</Level>
    <Cost>208</Cost>
    <Email>Dina@gmail.com</Email>
  </Engineer>
  <Engineer>
    <ID>200189976</ID>
    <Name>Shira</Name>
    <Level>Senior</Level>
    <Cost>177</Cost>
    <Email>Shira@gmail.com</Email>
  </Engineer>
  <Engineer>
    <ID>276575687</ID>
    <Name>Lea</Name>
    <Level>EIT</Level>
    <Cost>341</Cost>
    <Email>Lea@gmail.com</Email>
  </Engineer>
  <Engineer>
    <ID>280044684</ID>
    <Name>Rachel</Name>
    <Level>EIT</Level>
    <Cost>234</Cost>
    <Email>Rachel@gmail.com</Email>
  </Engineer>
  <Engineer>
    <ID>265858122</ID>
    <Name>Alice</Name>
    <Level>Senior</Level>
    <Cost>157</Cost>
    <Email>Alice@gmail.com</Email>
  </Engineer>
  <Engineer>
    <ID>373156570</ID>
    <Name>Dani</Name>
    <Level>Junior</Level>
    <Cost>120</Cost>
    <Email>Dani@gmail.com</Email>
  </Engineer>
  <Engineer>
    <ID>289358550</ID>
    <Name>Eli</Name>
    <Level>EIT</Level>
    <Cost>216</Cost>
    <Email>Eli@gmail.com</Email>
  </Engineer>
  <Engineer>
    <ID>353361397</ID>
    <Name>Yair</Name>
    <Level>Junior</Level>
    <Cost>110</Cost>
    <Email>Yair@gmail.com</Email>
  </Engineer>
  <Engineer>
    <ID>368435303</ID>
    <Name>Ariela</Name>
    <Level>EIT</Level>
    <Cost>265</Cost>
    <Email>Ariela@gmail.com</Email>
  </Engineer>
  <Engineer>
    <ID>394681982</ID>
    <Name>Dina</Name>
    <Level>Junior</Level>
    <Cost>325</Cost>
    <Email>Dina@gmail.com</Email>
  </Engineer>
  <Engineer>
    <ID>312808076</ID>
    <Name>Shira</Name>
    <Level>Senior</Level>
    <Cost>201</Cost>
    <Email>Shira@gmail.com</Email>
  </Engineer>
  <Engineer>
    <ID>305707913</ID>
    <Name>Lea</Name>
    <Level>EIT</Level>
    <Cost>312</Cost>
    <Email>Lea@gmail.com</Email>
  </Engineer>
  <Engineer>
    <ID>301815542</ID>
    <Name>Rachel</Name>
    <Level>EIT</Level>
    <Cost>222</Cost>
    <Email>Rachel@gmail.com</Email>
  </Engineer>
  <Engineer>
    <ID>376021241</ID>
    <Name>Alice</Name>
    <Level>Senior</Level>
    <Cost>329</Cost>
    <Email>Alice@gmail.com</Email>
  </Engineer>
  <Engineer>
    <ID>251500521</ID>
    <Name>Dani</Name>
    <Level>Junior</Level>
    <Cost>343</Cost>
    <Email>Dani@gmail.com</Email>
  </Engineer>
  <Engineer>
    <ID>241786031</ID>
    <Name>Eli</Name>
    <Level>EIT</Level>
    <Cost>119</Cost>
    <Email>Eli@gmail.com</Email>
  </Engineer>
  <Engineer>
    <ID>256789487</ID>
    <Name>Yair</Name>
    <Level>Junior</Level>
    <Cost>136</Cost>
    <Email>Yair@gmail.com</Email>
  </Engineer>
  <Engineer>
    <ID>338011035</ID>
    <Name>Ariela</Name>
    <Level>EIT</Level>
    <Cost>203</Cost>
    <Email>Ariela@gmail.com</Email>
  </Engineer>
  <Engineer>
    <ID>211392616</ID>
    <Name>Dina</Name>
    <Level>Junior</Level>
    <Cost>333</Cost>
    <Email>Dina@gmail.com</Email>
  </Engineer>
  <Engineer>
    <ID>228698331</ID>
    <Name>Shira</Name>
    <Level>Senior</Level>
    <Cost>151</Cost>
    <Email>Shira@gmail.com</Email>
  </Engineer>
  <Engineer>
    <ID>370870411</ID>
    <Name>Lea</Name>
    <Level>EIT</Level>
    <Cost>235</Cost>
    <Email>Lea@gmail.com</Email>
  </Engineer>
  <Engineer>
    <ID>252330049</ID>
    <Name>Rachel</Name>
    <Level>EIT</Level>
    <Cost>103</Cost>
    <Email>Rachel@gmail.com</Email>
  </Engineer>
  <Engineer>
    <ID>386255224</ID>
    <Name>Alice</Name>
    <Level>Senior</Level>
    <Cost>230</Cost>
    <Email>Alice@gmail.com</Email>
  </Engineer>
  <Engineer>
    <ID>274385925</ID>
    <Name>Dani</Name>
    <Level>Junior</Level>
    <Cost>145</Cost>
    <Email>Dani@gmail.com</Email>
  </Engineer>
  <Engineer>
    <ID>279086110</ID>
    <Name>Eli</Name>
    <Level>EIT</Level>
    <Cost>296</Cost>
    <Email>Eli@gmail.com</Email>
  </Engineer>
  <Engineer>
    <ID>383741719</ID>
    <Name>Yair</Name>
    <Level>Junior</Level>
    <Cost>271</Cost>
    <Email>Yair@gmail.com</Email>
  </Engineer>
  <Engineer>
    <ID>304738410</ID>
    <Name>Ariela</Name>
    <Level>EIT</Level>
    <Cost>278</Cost>
    <Email>Ariela@gmail.com</Email>
  </Engineer>
  <Engineer>
    <ID>383002558</ID>
    <Name>Dina</Name>
    <Level>Junior</Level>
    <Cost>204</Cost>
    <Email>Dina@gmail.com</Email>
  </Engineer>
  <Engineer>
    <ID>326149987</ID>
    <Name>Shira</Name>
    <Level>Senior</Level>
    <Cost>280</Cost>
    <Email>Shira@gmail.com</Email>
  </Engineer>
  <Engineer>
    <ID>214203067</ID>
    <Name>Lea</Name>
    <Level>EIT</Level>
    <Cost>148</Cost>
    <Email>Lea@gmail.com</Email>
  </Engineer>
  <Engineer>
    <ID>218023725</ID>
    <Name>Rachel</Name>
    <Level>EIT</Level>
    <Cost>263</Cost>
    <Email>Rachel@gmail.com</Email>
  </Engineer>
  <Engineer>
    <ID>250378343</ID>
    <Name>Alice</Name>
    <Level>Senior</Level>
    <Cost>343</Cost>
    <Email>Alice@gmail.com</Email>
  </Engineer>
  <Engineer>
    <ID>376722188</ID>
    <Name>Dani</Name>
    <Level>Junior</Level>
    <Cost>257</Cost>
    <Email>Dani@gmail.com</Email>
  </Engineer>
  <Engineer>
    <ID>292738594</ID>
    <Name>Eli</Name>
    <Level>EIT</Level>
    <Cost>300</Cost>
    <Email>Eli@gmail.com</Email>
  </Engineer>
  <Engineer>
    <ID>247082410</ID>
    <Name>Yair</Name>
    <Level>Junior</Level>
    <Cost>311</Cost>
    <Email>Yair@gmail.com</Email>
  </Engineer>
  <Engineer>
    <ID>201241853</ID>
    <Name>Ariela</Name>
    <Level>EIT</Level>
    <Cost>303</Cost>
    <Email>Ariela@gmail.com</Email>
  </Engineer>
  <Engineer>
    <ID>314635466</ID>
    <Name>Dina</Name>
    <Level>Junior</Level>
    <Cost>151</Cost>
    <Email>Dina@gmail.com</Email>
  </Engineer>
  <Engineer>
    <ID>397821582</ID>
    <Name>Shira</Name>
    <Level>Senior</Level>
    <Cost>254</Cost>
    <Email>Shira@gmail.com</Email>
  </Engineer>
  <Engineer>
    <ID>263403573</ID>
    <Name>Lea</Name>
    <Level>EIT</Level>
    <Cost>133</Cost>
    <Email>Lea@gmail.com</Email>
  </Engineer>
  <Engineer>
    <ID>308737648</ID>
    <Name>Rachel</Name>
    <Level>EIT</Level>
    <Cost>201</Cost>
    <Email>Rachel@gmail.com</Email>
  </Engineer>
  <Engineer>
    <ID>242465887</ID>
    <Name>Alice</Name>
    <Level>Senior</Level>
    <Cost>204</Cost>
    <Email>Alice@gmail.com</Email>
  </Engineer>
  <Engineer>
    <ID>221652724</ID>
    <Name>Dani</Name>
    <Level>Junior</Level>
    <Cost>168</Cost>
    <Email>Dani@gmail.com</Email>
  </Engineer>
  <Engineer>
    <ID>237216923</ID>
    <Name>Eli</Name>
    <Level>EIT</Level>
    <Cost>116</Cost>
    <Email>Eli@gmail.com</Email>
  </Engineer>
  <Engineer>
    <ID>236481479</ID>
    <Name>Yair</Name>
    <Level>Junior</Level>
    <Cost>306</Cost>
    <Email>Yair@gmail.com</Email>
  </Engineer>
  <Engineer>
    <ID>394864398</ID>
    <Name>Ariela</Name>
    <Level>EIT</Level>
    <Cost>339</Cost>
    <Email>Ariela@gmail.com</Email>
  </Engineer>
  <Engineer>
    <ID>223609855</ID>
    <Name>Dina</Name>
    <Level>Junior</Level>
    <Cost>219</Cost>
    <Email>Dina@gmail.com</Email>
  </Engineer>
  <Engineer>
    <ID>256881944</ID>
    <Name>Shira</Name>
    <Level>Senior</Level>
    <Cost>290</Cost>
    <Email>Shira@gmail.com</Email>
  </Engineer>
  <Engineer>
    <ID>249189305</ID>
    <Name>Lea</Name>
    <Level>EIT</Level>
    <Cost>248</Cost>
    <Email>Lea@gmail.com</Email>
  </Engineer>
  <Engineer>
    <ID>335037219</ID>
    <Name>Rachel</Name>
    <Level>EIT</Level>
    <Cost>150</Cost>
    <Email>Rachel@gmail.com</Email>
  </Engineer>
  <Engineer>
    <ID>217491055</ID>
    <Name>Alice</Name>
    <Level>Senior</Level>
    <Cost>330</Cost>
    <Email>Alice@gmail.com</Email>
  </Engineer>
  <Engineer>
    <ID>300608264</ID>
    <Name>Dani</Name>
    <Level>Junior</Level>
    <Cost>346</Cost>
    <Email>Dani@gmail.com</Email>
  </Engineer>
  <Engineer>
    <ID>278931513</ID>
    <Name>Eli</Name>
    <Level>EIT</Level>
    <Cost>269</Cost>
    <Email>Eli@gmail.com</Email>
  </Engineer>
  <Engineer>
    <ID>207554890</ID>
    <Name>Yair</Name>
    <Level>Junior</Level>
    <Cost>261</Cost>
    <Email>Yair@gmail.com</Email>
  </Engineer>
  <Engineer>
    <ID>360875753</ID>
    <Name>Ariela</Name>
    <Level>EIT</Level>
    <Cost>253</Cost>
    <Email>Ariela@gmail.com</Email>
  </Engineer>
  <Engineer>
    <ID>224920293</ID>
    <Name>Dina</Name>
    <Level>Junior</Level>
    <Cost>110</Cost>
    <Email>Dina@gmail.com</Email>
  </Engineer>
  <Engineer>
    <ID>251906737</ID>
    <Name>Shira</Name>
    <Level>Senior</Level>
    <Cost>238</Cost>
    <Email>Shira@gmail.com</Email>
  </Engineer>
  <Engineer>
    <ID>220418449</ID>
    <Name>Lea</Name>
    <Level>EIT</Level>
    <Cost>219</Cost>
    <Email>Lea@gmail.com</Email>
  </Engineer>
  <Engineer>
    <ID>319739414</ID>
    <Name>Rachel</Name>
    <Level>EIT</Level>
    <Cost>121</Cost>
    <Email>Rachel@gmail.com</Email>
  </Engineer>
  <Engineer>
    <ID>363016701</ID>
    <Name>Alice</Name>
    <Level>Senior</Level>
    <Cost>193</Cost>
    <Email>Alice@gmail.com</Email>
  </Engineer>
  <Engineer>
    <ID>327638347</ID>
    <Name>Dani</Name>
    <Level>Junior</Level>
    <Cost>115</Cost>
    <Email>Dani@gmail.com</Email>
  </Engineer>
  <Engineer>
    <ID>285371952</ID>
    <Name>Eli</Name>
    <Level>EIT</Level>
    <Cost>321</Cost>
    <Email>Eli@gmail.com</Email>
  </Engineer>
  <Engineer>
    <ID>371232555</ID>
    <Name>Yair</Name>
    <Level>Junior</Level>
    <Cost>329</Cost>
    <Email>Yair@gmail.com</Email>
  </Engineer>
  <Engineer>
    <ID>309584803</ID>
    <Name>Ariela</Name>
    <Level>EIT</Level>
    <Cost>201</Cost>
    <Email>Ariela@gmail.com</Email>
  </Engineer>
  <Engineer>
    <ID>206928914</ID>
    <Name>Dina</Name>
    <Level>Junior</Level>
    <Cost>260</Cost>
    <Email>Dina@gmail.com</Email>
  </Engineer>
  <Engineer>
    <ID>339501636</ID>
    <Name>Shira</Name>
    <Level>Senior</Level>
    <Cost>230</Cost>
    <Email>Shira@gmail.com</Email>
  </Engineer>
  <Engineer>
    <ID>290640554</ID>
    <Name>Lea</Name>
    <Level>EIT</Level>
    <Cost>103</Cost>
    <Email>Lea@gmail.com</Email>
  </Engineer>
  <Engineer>
    <ID>215086711</ID>
    <Name>Rachel</Name>
    <Level>EIT</Level>
    <Cost>282</Cost>
    <Email>Rachel@gmail.com</Email>
  </Engineer>
  <Engineer>
    <ID>222320064</ID>
    <Name>Alice</Name>
    <Level>Senior</Level>
    <Cost>181</Cost>
    <Email>Alice@gmail.com</Email>
  </Engineer>
  <Engineer>
    <ID>237662084</ID>
    <Name>Dani</Name>
    <Level>Junior</Level>
    <Cost>238</Cost>
    <Email>Dani@gmail.com</Email>
  </Engineer>
  <Engineer>
    <ID>236567110</ID>
    <Name>Eli</Name>
    <Level>EIT</Level>
    <Cost>173</Cost>
    <Email>Eli@gmail.com</Email>
  </Engineer>
  <Engineer>
    <ID>323049354</ID>
    <Name>Yair</Name>
    <Level>Junior</Level>
    <Cost>315</Cost>
    <Email>Yair@gmail.com</Email>
  </Engineer>
  <Engineer>
    <ID>381874251</ID>
    <Name>Ariela</Name>
    <Level>EIT</Level>
    <Cost>167</Cost>
    <Email>Ariela@gmail.com</Email>
  </Engineer>
  <Engineer>
    <ID>258011003</ID>
    <Name>Dina</Name>
    <Level>Junior</Level>
    <Cost>110</Cost>
    <Email>Dina@gmail.com</Email>
  </Engineer>
  <Engineer>
    <ID>377704632</ID>
    <Name>Shira</Name>
    <Level>Senior</Level>
    <Cost>306</Cost>
    <Email>Shira@gmail.com</Email>
  </Engineer>
  <Engineer>
    <ID>229158955</ID>
    <Name>Lea</Name>
    <Level>EIT</Level>
    <Cost>328</Cost>
    <Email>Lea@gmail.com</Email>
  </Engineer>
  <Engineer>
    <ID>295402199</ID>
    <Name>Rachel</Name>
    <Level>EIT</Level>
    <Cost>108</Cost>
    <Email>Rachel@gmail.com</Email>
  </Engineer>
  <Engineer>
    <ID>203330883</ID>
    <Name>SARI</Name>
    <Level>Senior</Level>
    <Cost>189</Cost>
    <Email>Alice@gmail.com</Email>
  </Engineer>
  <Engineer>
    <ID>236849225</ID>
    <Name>Dani</Name>
    <Level>Junior</Level>
    <Cost>171</Cost>
    <Email>Dani@gmail.com</Email>
  </Engineer>
  <Engineer>
    <ID>240613957</ID>
    <Name>Eli</Name>
    <Level>EIT</Level>
    <Cost>255</Cost>
    <Email>Eli@gmail.com</Email>
  </Engineer>
  <Engineer>
    <ID>242159249</ID>
    <Name>Yair</Name>
    <Level>Junior</Level>
    <Cost>198</Cost>
    <Email>Yair@gmail.com</Email>
  </Engineer>
  <Engineer>
    <ID>228349158</ID>
    <Name>Ariela</Name>
    <Level>EIT</Level>
    <Cost>281</Cost>
    <Email>Ariela@gmail.com</Email>
  </Engineer>
  <Engineer>
    <ID>320907794</ID>
    <Name>Dina</Name>
    <Level>Junior</Level>
    <Cost>285</Cost>
    <Email>Dina@gmail.com</Email>
  </Engineer>
  <Engineer>
    <ID>357469228</ID>
    <Name>Shira</Name>
    <Level>Senior</Level>
    <Cost>124</Cost>
    <Email>Shira@gmail.com</Email>
  </Engineer>
  <Engineer>
    <ID>290986896</ID>
    <Name>Lea</Name>
    <Level>EIT</Level>
    <Cost>160</Cost>
    <Email>Lea@gmail.com</Email>
  </Engineer>
  <Engineer>
    <ID>336509317</ID>
    <Name>Rachel</Name>
    <Level>EIT</Level>
    <Cost>341</Cost>
    <Email>Rachel@gmail.com</Email>
  </Engineer>
  <Engineer>
    <ID>311406554</ID>
    <Name>Alice</Name>
    <Level>Senior</Level>
    <Cost>266</Cost>
    <Email>Alice@gmail.com</Email>
  </Engineer>
  <Engineer>
    <ID>256736576</ID>
    <Name>Dani</Name>
    <Level>Junior</Level>
    <Cost>201</Cost>
    <Email>Dani@gmail.com</Email>
  </Engineer>
  <Engineer>
    <ID>240674459</ID>
    <Name>Eli</Name>
    <Level>EIT</Level>
    <Cost>156</Cost>
    <Email>Eli@gmail.com</Email>
  </Engineer>
  <Engineer>
    <ID>250108509</ID>
    <Name>Yair</Name>
    <Level>Junior</Level>
    <Cost>339</Cost>
    <Email>Yair@gmail.com</Email>
  </Engineer>
  <Engineer>
    <ID>239773494</ID>
    <Name>Ariela</Name>
    <Level>EIT</Level>
    <Cost>332</Cost>
    <Email>Ariela@gmail.com</Email>
  </Engineer>
  <Engineer>
    <ID>377047505</ID>
    <Name>Dina</Name>
    <Level>Junior</Level>
    <Cost>146</Cost>
    <Email>Dina@gmail.com</Email>
  </Engineer>
  <Engineer>
    <ID>346288091</ID>
    <Name>Shira</Name>
    <Level>Senior</Level>
    <Cost>275</Cost>
    <Email>Shira@gmail.com</Email>
  </Engineer>
  <Engineer>
    <ID>257925132</ID>
    <Name>Lea</Name>
    <Level>EIT</Level>
    <Cost>264</Cost>
    <Email>Lea@gmail.com</Email>
  </Engineer>
  <Engineer>
    <ID>384363768</ID>
    <Name>Rachel</Name>
    <Level>EIT</Level>
    <Cost>215</Cost>
    <Email>Rachel@gmail.com</Email>
  </Engineer>
  <Engineer>
    <ID>227285280</ID>
    <Name>Alice</Name>
    <Level>Senior</Level>
    <Cost>118</Cost>
    <Email>Alice@gmail.com</Email>
  </Engineer>
  <Engineer>
    <ID>327047563</ID>
    <Name>Dani</Name>
    <Level>Junior</Level>
    <Cost>160</Cost>
    <Email>Dani@gmail.com</Email>
  </Engineer>
  <Engineer>
    <ID>214027016</ID>
    <Name>Eli</Name>
    <Level>EIT</Level>
    <Cost>225</Cost>
    <Email>Eli@gmail.com</Email>
  </Engineer>
  <Engineer>
    <ID>382204236</ID>
    <Name>Yair</Name>
    <Level>Junior</Level>
    <Cost>124</Cost>
    <Email>Yair@gmail.com</Email>
  </Engineer>
  <Engineer>
    <ID>322334391</ID>
    <Name>Ariela</Name>
    <Level>EIT</Level>
    <Cost>185</Cost>
    <Email>Ariela@gmail.com</Email>
  </Engineer>
  <Engineer>
    <ID>364144041</ID>
    <Name>Dina</Name>
    <Level>Junior</Level>
    <Cost>252</Cost>
    <Email>Dina@gmail.com</Email>
  </Engineer>
  <Engineer>
    <ID>391136608</ID>
    <Name>Shira</Name>
    <Level>Senior</Level>
    <Cost>263</Cost>
    <Email>Shira@gmail.com</Email>
  </Engineer>
  <Engineer>
    <ID>372443765</ID>
    <Name>Lea</Name>
    <Level>EIT</Level>
    <Cost>159</Cost>
    <Email>Lea@gmail.com</Email>
  </Engineer>
  <Engineer>
    <ID>200500028</ID>
    <Name>Rachel</Name>
    <Level>EIT</Level>
    <Cost>218</Cost>
    <Email>Rachel@gmail.com</Email>
  </Engineer>
  <Engineer>
    <ID>235154408</ID>
    <Name>Alice</Name>
    <Level>Senior</Level>
    <Cost>268</Cost>
    <Email>Alice@gmail.com</Email>
  </Engineer>
  <Engineer>
    <ID>342009210</ID>
    <Name>Dani</Name>
    <Level>Junior</Level>
    <Cost>110</Cost>
    <Email>Dani@gmail.com</Email>
  </Engineer>
  <Engineer>
    <ID>257492125</ID>
    <Name>Eli</Name>
    <Level>EIT</Level>
    <Cost>189</Cost>
    <Email>Eli@gmail.com</Email>
  </Engineer>
  <Engineer>
    <ID>369071403</ID>
    <Name>Yair</Name>
    <Level>Junior</Level>
    <Cost>183</Cost>
    <Email>Yair@gmail.com</Email>
  </Engineer>
  <Engineer>
    <ID>387133127</ID>
    <Name>Ariela</Name>
    <Level>EIT</Level>
    <Cost>289</Cost>
    <Email>Ariela@gmail.com</Email>
  </Engineer>
  <Engineer>
    <ID>269021943</ID>
    <Name>Dina</Name>
    <Level>Junior</Level>
    <Cost>290</Cost>
    <Email>Dina@gmail.com</Email>
  </Engineer>
  <Engineer>
    <ID>265765179</ID>
    <Name>Shira</Name>
    <Level>Senior</Level>
    <Cost>122</Cost>
    <Email>Shira@gmail.com</Email>
  </Engineer>
  <Engineer>
    <ID>233585745</ID>
    <Name>Lea</Name>
    <Level>EIT</Level>
    <Cost>103</Cost>
    <Email>Lea@gmail.com</Email>
  </Engineer>
  <Engineer>
    <ID>333389149</ID>
    <Name>Rachel</Name>
    <Level>EIT</Level>
    <Cost>141</Cost>
    <Email>Rachel@gmail.com</Email>
  </Engineer>
  <Engineer>
    <ID>300873025</ID>
    <Name>Alice</Name>
    <Level>Senior</Level>
    <Cost>283</Cost>
    <Email>Alice@gmail.com</Email>
  </Engineer>
  <Engineer>
    <ID>234071750</ID>
    <Name>Dani</Name>
    <Level>Junior</Level>
    <Cost>123</Cost>
    <Email>Dani@gmail.com</Email>
  </Engineer>
  <Engineer>
    <ID>319997676</ID>
    <Name>Eli</Name>
    <Level>EIT</Level>
    <Cost>250</Cost>
    <Email>Eli@gmail.com</Email>
  </Engineer>
  <Engineer>
    <ID>224544843</ID>
    <Name>Yair</Name>
    <Level>Junior</Level>
    <Cost>101</Cost>
    <Email>Yair@gmail.com</Email>
  </Engineer>
  <Engineer>
    <ID>352204619</ID>
    <Name>Ariela</Name>
    <Level>EIT</Level>
    <Cost>135</Cost>
    <Email>Ariela@gmail.com</Email>
  </Engineer>
  <Engineer>
    <ID>382961213</ID>
    <Name>Dina</Name>
    <Level>Junior</Level>
    <Cost>184</Cost>
    <Email>Dina@gmail.com</Email>
  </Engineer>
  <Engineer>
    <ID>222201460</ID>
    <Name>Shira</Name>
    <Level>Senior</Level>
    <Cost>262</Cost>
    <Email>Shira@gmail.com</Email>
  </Engineer>
  <Engineer>
    <ID>308909631</ID>
    <Name>Lea</Name>
    <Level>EIT</Level>
    <Cost>335</Cost>
    <Email>Lea@gmail.com</Email>
  </Engineer>
  <Engineer>
    <ID>362647057</ID>
    <Name>Rachel</Name>
    <Level>EIT</Level>
    <Cost>310</Cost>
    <Email>Rachel@gmail.com</Email>
  </Engineer>
  <Engineer>
    <ID>240135354</ID>
    <Name>Alice</Name>
    <Level>Senior</Level>
    <Cost>249</Cost>
    <Email>Alice@gmail.com</Email>
  </Engineer>
</ArrayOfEngineer>